sklearn_diagnose/__init__.py
sklearn_diagnose/api/__init__.py
sklearn_diagnose/api/diagnose.py
sklearn_diagnose/core/__init__.py
sklearn_diagnose/core/evidence.py
sklearn_diagnose/core/hypotheses.py
sklearn_diagnose/core/recommendations.py
sklearn_diagnose/core/schemas.py
sklearn_diagnose/core/signals.py
sklearn_diagnose/llm/__init__.py
sklearn_diagnose/llm/client.py
sklearn_diagnose-0.1.0.dist-info/licenses/LICENSE
sklearn_diagnose-0.1.0.dist-info/METADATA
sklearn_diagnose-0.1.0.dist-info/WHEEL
sklearn_diagnose-0.1.0.dist-info/top_level.txt
sklearn_diagnose-0.1.0.dist-info/RECORD
