Metadata-Version: 2.4
Name: sklearn-diagnose
Version: 0.1.0
Summary: An intelligent diagnosis layer for scikit-learn: evidence-based model failure detection with LLM-powered summaries
Author: sklearn-diagnose contributors
License: MIT
Project-URL: Homepage, https://github.com/leockl/sklearn-diagnose
Project-URL: Documentation, https://github.com/leockl/sklearn-diagnose#readme
Project-URL: Repository, https://github.com/leockl/sklearn-diagnose
Project-URL: Issues, https://github.com/leockl/sklearn-diagnose/issues
Keywords: machine-learning,scikit-learn,sklearn,diagnostics,model-debugging,llm,explainability,cross-validation,overfitting,underfitting
Classifier: Development Status :: 3 - Alpha
Classifier: Intended Audience :: Developers
Classifier: Intended Audience :: Science/Research
Classifier: License :: OSI Approved :: MIT License
Classifier: Operating System :: OS Independent
Classifier: Programming Language :: Python :: 3
Classifier: Programming Language :: Python :: 3.9
Classifier: Programming Language :: Python :: 3.10
Classifier: Programming Language :: Python :: 3.11
Classifier: Programming Language :: Python :: 3.12
Classifier: Topic :: Scientific/Engineering :: Artificial Intelligence
Classifier: Topic :: Software Development :: Libraries :: Python Modules
Requires-Python: >=3.9
License-File: LICENSE
Requires-Dist: scikit-learn>=1.0.0
Requires-Dist: numpy>=1.21.0
Requires-Dist: pandas>=1.3.0
Requires-Dist: scipy>=1.7.0
Requires-Dist: langchain>=1.2.0
Requires-Dist: langchain-openai>=0.3.0
Requires-Dist: langchain-anthropic>=0.3.0
Requires-Dist: langchain-core>=0.3.0
Requires-Dist: langgraph>=0.4.0
Requires-Dist: pydantic>=2.0.0
Requires-Dist: python-dotenv>=1.0.0
Provides-Extra: dev
Requires-Dist: pytest>=7.0.0; extra == "dev"
Requires-Dist: pytest-cov>=4.0.0; extra == "dev"
Requires-Dist: black>=23.0.0; extra == "dev"
Requires-Dist: ruff>=0.1.0; extra == "dev"
Requires-Dist: mypy>=1.0.0; extra == "dev"
Dynamic: license-file
